satsie/__init__.py
satsie/settings.py
satsie/subscription.py
satsie/utils.py
satsie-1.0.0.dist-info/LICENSE
satsie-1.0.0.dist-info/METADATA
satsie-1.0.0.dist-info/WHEEL
satsie-1.0.0.dist-info/entry_points.txt
satsie-1.0.0.dist-info/top_level.txt
satsie-1.0.0.dist-info/RECORD
