Metadata-Version: 2.1
Name: satsie
Version: 1.0.0
Summary: a tool to check for your subscription updates.
Home-page: https://github.com/vjyq/satsie.git
Author: vjyq
Author-email: yuqing.ji@outlook.com
License: UNKNOWN
Platform: UNKNOWN
Classifier: License :: OSI Approved :: GNU General Public License v3 (GPLv3)
Classifier: Programming Language :: Python :: 2.7
Requires-Dist: atomicwrites (==1.3.0)
Requires-Dist: attrs (==19.1.0)
Requires-Dist: bleach (==3.1.0)
Requires-Dist: certifi (==2019.3.9)
Requires-Dist: chardet (==3.0.4)
Requires-Dist: Click (==7.0)
Requires-Dist: docutils (==0.14)
Requires-Dist: funcsigs (==1.0.2)
Requires-Dist: idna (==2.8)
Requires-Dist: more-itertools (==5.0.0)
Requires-Dist: pathlib2 (==2.3.3)
Requires-Dist: pkginfo (==1.5.0.1)
Requires-Dist: pluggy (==0.9.0)
Requires-Dist: py (==1.8.0)
Requires-Dist: Pygments (==2.3.1)
Requires-Dist: pytest (==4.3.1)
Requires-Dist: readme-renderer (==24.0)
Requires-Dist: requests (==2.21.0)
Requires-Dist: requests-toolbelt (==0.9.1)
Requires-Dist: scandir (==1.10.0)
Requires-Dist: six (==1.12.0)
Requires-Dist: tqdm (==4.31.1)
Requires-Dist: twine (==1.13.0)
Requires-Dist: urllib3 (==1.24.1)
Requires-Dist: webencodings (==0.5.1)
